cowsay/conf.py
cowsay/version.py
cowsay/grains/cowsay.py
grains_cow_fortune-2.dist-info/METADATA
grains_cow_fortune-2.dist-info/WHEEL
grains_cow_fortune-2.dist-info/top_level.txt
grains_cow_fortune-2.dist-info/RECORD
