Metadata-Version: 2.1
Name: grains-cow-fortune
Version: 2
Summary: Vertically extends the POP-based grains project and adds the cowsay and fortune GRAINS
Home-page: https://gitlab.com/Akm0d/corn_cowsay
Author: Tyler Johnson
Author-email: tjohnson@saltstack.com
License: UNKNOWN
Platform: UNKNOWN
Classifier: Operating System :: OS Independent
Classifier: Programming Language :: Python
Classifier: Programming Language :: Python :: 3.6
Classifier: Programming Language :: Python :: 3.7
Classifier: Programming Language :: Python :: 3.8
Classifier: Development Status :: 5 - Production/Stable
Requires-Python: >=3.6
Requires-Dist: cowsay (>=2.0.3)
Requires-Dist: pop (>=13)
Requires-Dist: grainsv2
